{
"meta":{"test_sets":[],"test_metrics":[],"learn_metrics":[{"best_value":"Min","name":"QueryRMSE"}],"launch_mode":"Train","parameters":"","iteration_count":300,"learn_sets":["learn"],"name":"experiment"},
"iterations":[
{"learn":[5.504699993],"iteration":0,"passed_time":0.0008811568531,"remaining_time":0.2634658991},
{"learn":[5.288042844],"iteration":1,"passed_time":0.001691804327,"remaining_time":0.2520788447},
{"learn":[5.099071289],"iteration":2,"passed_time":0.002455365401,"remaining_time":0.2430811747},
{"learn":[4.955183501],"iteration":3,"passed_time":0.003251375813,"remaining_time":0.2406018102},
{"learn":[4.813045337],"iteration":4,"passed_time":0.004025556373,"remaining_time":0.237507826},
{"learn":[4.688349357],"iteration":5,"passed_time":0.004786903589,"remaining_time":0.2345582759},
{"learn":[4.585894702],"iteration":6,"passed_time":0.005586100256,"remaining_time":0.2338181964},
{"learn":[4.500714281],"iteration":7,"passed_time":0.006413107953,"remaining_time":0.2340784403},
{"learn":[4.42724792],"iteration":8,"passed_time":0.007186947888,"remaining_time":0.2323779817},
{"learn":[4.346794441],"iteration":9,"passed_time":0.007943776609,"remaining_time":0.2303695217},
{"learn":[4.286219688],"iteration":10,"passed_time":0.008686389449,"remaining_time":0.228215141},
{"learn":[4.224910766],"iteration":11,"passed_time":0.009445773062,"remaining_time":0.2266985535},
{"learn":[4.18664916],"iteration":12,"passed_time":0.01021328138,"remaining_time":0.2254778274},
{"learn":[4.148350766],"iteration":13,"passed_time":0.01099634804,"remaining_time":0.2246396814},
{"learn":[4.106826171],"iteration":14,"passed_time":0.01173648613,"remaining_time":0.2229932366},
{"learn":[4.06673928],"iteration":15,"passed_time":0.0124849996,"remaining_time":0.2216087429},
{"learn":[4.044339718],"iteration":16,"passed_time":0.01328020854,"remaining_time":0.2210764127},
{"learn":[4.01299645],"iteration":17,"passed_time":0.01414020657,"remaining_time":0.2215299029},
{"learn":[3.983389957],"iteration":18,"passed_time":0.01491065007,"remaining_time":0.2205206668},
{"learn":[3.958906554],"iteration":19,"passed_time":0.01569801482,"remaining_time":0.2197722075},
{"learn":[3.937295992],"iteration":20,"passed_time":0.01642760335,"remaining_time":0.2182524445},
{"learn":[3.915342637],"iteration":21,"passed_time":0.01719507159,"remaining_time":0.2172831774},
{"learn":[3.894335358],"iteration":22,"passed_time":0.01798029241,"remaining_time":0.2165452608},
{"learn":[3.875333927],"iteration":23,"passed_time":0.01871677359,"remaining_time":0.2152428963},
{"learn":[3.860746163],"iteration":24,"passed_time":0.01947858165,"remaining_time":0.2142643982},
{"learn":[3.84788919],"iteration":25,"passed_time":0.02027558409,"remaining_time":0.2136734631},
{"learn":[3.833221543],"iteration":26,"passed_time":0.02108820539,"remaining_time":0.2132251878},
{"learn":[3.820902983],"iteration":27,"passed_time":0.02183713963,"remaining_time":0.2121322135},
{"learn":[3.809972159],"iteration":28,"passed_time":0.0226075635,"remaining_time":0.211263783},
{"learn":[3.801510637],"iteration":29,"passed_time":0.02335668829,"remaining_time":0.2102101946},
{"learn":[3.787834292],"iteration":30,"passed_time":0.02406608017,"remaining_time":0.2088314698},
{"learn":[3.779155031],"iteration":31,"passed_time":0.02484989841,"remaining_time":0.2081178992},
{"learn":[3.769072029],"iteration":32,"passed_time":0.02559000625,"remaining_time":0.2070464142},
{"learn":[3.759394792],"iteration":33,"passed_time":0.02632923246,"remaining_time":0.2059875246},
{"learn":[3.751129232],"iteration":34,"passed_time":0.02706423092,"remaining_time":0.2049148913},
{"learn":[3.742734782],"iteration":35,"passed_time":0.02781735284,"remaining_time":0.2039939209},
{"learn":[3.735833469],"iteration":36,"passed_time":0.02856579597,"remaining_time":0.203048766},
{"learn":[3.729151833],"iteration":37,"passed_time":0.02935848028,"remaining_time":0.2024189956},
{"learn":[3.721087591],"iteration":38,"passed_time":0.03007348246,"remaining_time":0.201260998},
{"learn":[3.714460158],"iteration":39,"passed_time":0.03077592117,"remaining_time":0.2000434876},
{"learn":[3.708253179],"iteration":40,"passed_time":0.03152228089,"remaining_time":0.1991285549},
{"learn":[3.699973043],"iteration":41,"passed_time":0.03223334564,"remaining_time":0.1980048375},
{"learn":[3.694898135],"iteration":42,"passed_time":0.03302010929,"remaining_time":0.1973527462},
{"learn":[3.689605317],"iteration":43,"passed_time":0.03378997172,"remaining_time":0.1965961991},
{"learn":[3.684069593],"iteration":44,"passed_time":0.03452316728,"remaining_time":0.1956312812},
{"learn":[3.678718383],"iteration":45,"passed_time":0.0353117645,"remaining_time":0.1949823518},
{"learn":[3.670224587],"iteration":46,"passed_time":0.03608783833,"remaining_time":0.1942600659},
{"learn":[3.66538291],"iteration":47,"passed_time":0.03683494921,"remaining_time":0.1933834834},
{"learn":[3.660985037],"iteration":48,"passed_time":0.03758207033,"remaining_time":0.1925122378},
{"learn":[3.653107201],"iteration":49,"passed_time":0.03832453269,"remaining_time":0.1916226634},
{"learn":[3.646897269],"iteration":50,"passed_time":0.0390661535,"remaining_time":0.1907347495},
{"learn":[3.64241597],"iteration":51,"passed_time":0.0398247655,"remaining_time":0.189933497},
{"learn":[3.639676153],"iteration":52,"passed_time":0.04059843491,"remaining_time":0.1892040269},
{"learn":[3.631225962],"iteration":53,"passed_time":0.04133318312,"remaining_time":0.188295612},
{"learn":[3.625242241],"iteration":54,"passed_time":0.04213638673,"remaining_time":0.18769845},
{"learn":[3.622320968],"iteration":55,"passed_time":0.04288270596,"remaining_time":0.186846076},
{"learn":[3.61720514],"iteration":56,"passed_time":0.04363492623,"remaining_time":0.1860225802},
{"learn":[3.613440107],"iteration":57,"passed_time":0.04438977131,"remaining_time":0.1852124941},
{"learn":[3.610327596],"iteration":58,"passed_time":0.04511779738,"remaining_time":0.1842947317},
{"learn":[3.605864367],"iteration":59,"passed_time":0.04588482482,"remaining_time":0.1835392993},
{"learn":[3.601019808],"iteration":60,"passed_time":0.04660336328,"remaining_time":0.1825935053},
{"learn":[3.596014553],"iteration":61,"passed_time":0.04734251957,"remaining_time":0.181734188},
{"learn":[3.591501835],"iteration":62,"passed_time":0.04806853175,"remaining_time":0.1808292385},
{"learn":[3.589131579],"iteration":63,"passed_time":0.048838184,"remaining_time":0.1800908035},
{"learn":[3.585540276],"iteration":64,"passed_time":0.04957593772,"remaining_time":0.1792360825},
{"learn":[3.581820597],"iteration":65,"passed_time":0.05031626636,"remaining_time":0.1783940353},
{"learn":[3.578802417],"iteration":66,"passed_time":0.05105045354,"remaining_time":0.1775336668},
{"learn":[3.574297185],"iteration":67,"passed_time":0.05176214924,"remaining_time":0.1766002739},
{"learn":[3.57017845],"iteration":68,"passed_time":0.05248078789,"remaining_time":0.1756965507},
{"learn":[3.567887209],"iteration":69,"passed_time":0.05322190778,"remaining_time":0.1748719827},
{"learn":[3.563769306],"iteration":70,"passed_time":0.05397308614,"remaining_time":0.1740822074},
{"learn":[3.560038072],"iteration":71,"passed_time":0.05469862724,"remaining_time":0.1732123196},
{"learn":[3.55869398],"iteration":72,"passed_time":0.05543783383,"remaining_time":0.1723888805},
{"learn":[3.555155365],"iteration":73,"passed_time":0.05618150862,"remaining_time":0.1715813642},
{"learn":[3.551728551],"iteration":74,"passed_time":0.05693081374,"remaining_time":0.1707924412},
{"learn":[3.545625639],"iteration":75,"passed_time":0.05768554882,"remaining_time":0.170020565},
{"learn":[3.542456031],"iteration":76,"passed_time":0.05843847037,"remaining_time":0.1692438817},
{"learn":[3.538945006],"iteration":77,"passed_time":0.05919492862,"remaining_time":0.1684778738},
{"learn":[3.536623898],"iteration":78,"passed_time":0.05995897058,"remaining_time":0.1677333227},
{"learn":[3.533676269],"iteration":79,"passed_time":0.06069919904,"remaining_time":0.1669227974},
{"learn":[3.527592006],"iteration":80,"passed_time":0.06141526317,"remaining_time":0.1660486745},
{"learn":[3.524139471],"iteration":81,"passed_time":0.06216152229,"remaining_time":0.1652586812},
{"learn":[3.522082996],"iteration":82,"passed_time":0.062916167,"remaining_time":0.1644916655},
{"learn":[3.518741565],"iteration":83,"passed_time":0.0636504241,"remaining_time":0.1636725191},
{"learn":[3.515446127],"iteration":84,"passed_time":0.0643586334,"remaining_time":0.1627894845},
{"learn":[3.512465723],"iteration":85,"passed_time":0.06508192058,"remaining_time":0.1619480349},
{"learn":[3.508506339],"iteration":86,"passed_time":0.06582720812,"remaining_time":0.1611631647},
{"learn":[3.506548926],"iteration":87,"passed_time":0.06656098475,"remaining_time":0.1603514633},
{"learn":[3.502665034],"iteration":88,"passed_time":0.06728954159,"remaining_time":0.1595291379},
{"learn":[3.49928836],"iteration":89,"passed_time":0.06798941601,"remaining_time":0.1586419707},
{"learn":[3.49451024],"iteration":90,"passed_time":0.068729494,"remaining_time":0.1578512554},
{"learn":[3.490625601],"iteration":91,"passed_time":0.06946811911,"remaining_time":0.1570583562},
{"learn":[3.486876121],"iteration":92,"passed_time":0.07018333147,"remaining_time":0.156214512},
{"learn":[3.483216034],"iteration":93,"passed_time":0.07093872776,"remaining_time":0.1554614672},
{"learn":[3.481496094],"iteration":94,"passed_time":0.07164128711,"remaining_time":0.1545943564},
{"learn":[3.480058936],"iteration":95,"passed_time":0.07234396627,"remaining_time":0.1537309283},
{"learn":[3.476602618],"iteration":96,"passed_time":0.07307884451,"remaining_time":0.1529382004},
{"learn":[3.471741388],"iteration":97,"passed_time":0.07378792561,"remaining_time":0.1520934793},
{"learn":[3.468182886],"iteration":98,"passed_time":0.07452126143,"remaining_time":0.1513007429},
{"learn":[3.463525219],"iteration":99,"passed_time":0.07525041938,"remaining_time":0.1505008388},
{"learn":[3.460913013],"iteration":100,"passed_time":0.07596821648,"remaining_time":0.1496799513},
{"learn":[3.457005666],"iteration":101,"passed_time":0.07665616861,"remaining_time":0.1488031508},
{"learn":[3.455320188],"iteration":102,"passed_time":0.07736230431,"remaining_time":0.1479647956},
{"learn":[3.452797916],"iteration":103,"passed_time":0.07809635123,"remaining_time":0.147181585},
{"learn":[3.450377142],"iteration":104,"passed_time":0.07881856624,"remaining_time":0.1463773373},
{"learn":[3.447837821],"iteration":105,"passed_time":0.07953497099,"remaining_time":0.1455640035},
{"learn":[3.444810096],"iteration":106,"passed_time":0.08024991305,"remaining_time":0.1447498432},
{"learn":[3.439260184],"iteration":107,"passed_time":0.08100757309,"remaining_time":0.1440134633},
{"learn":[3.434438926],"iteration":108,"passed_time":0.08174012748,"remaining_time":0.1432327004},
{"learn":[3.431000734],"iteration":109,"passed_time":0.08248205907,"remaining_time":0.1424690111},
{"learn":[3.428388003],"iteration":110,"passed_time":0.08320512584,"remaining_time":0.1416735926},
{"learn":[3.424834179],"iteration":111,"passed_time":0.08392603845,"remaining_time":0.1408758503},
{"learn":[3.421548455],"iteration":112,"passed_time":0.08468557214,"remaining_time":0.1401433804},
{"learn":[3.417418405],"iteration":113,"passed_time":0.08540858861,"remaining_time":0.1393508551},
{"learn":[3.416068714],"iteration":114,"passed_time":0.08608957817,"remaining_time":0.1384919301},
{"learn":[3.41260559],"iteration":115,"passed_time":0.08682638035,"remaining_time":0.1377246033},
{"learn":[3.410415138],"iteration":116,"passed_time":0.08756831153,"remaining_time":0.1369658206},
{"learn":[3.408792321],"iteration":117,"passed_time":0.08826024117,"remaining_time":0.1361302025},
{"learn":[3.405165824],"iteration":118,"passed_time":0.08898432981,"remaining_time":0.1353459134},
{"learn":[3.401273205],"iteration":119,"passed_time":0.08971884739,"remaining_time":0.1345782711},
{"learn":[3.39733942],"iteration":120,"passed_time":0.09045553916,"remaining_time":0.1338143926},
{"learn":[3.392557522],"iteration":121,"passed_time":0.09120906181,"remaining_time":0.1330755164},
{"learn":[3.388296579],"iteration":122,"passed_time":0.09194092472,"remaining_time":0.1323052331},
{"learn":[3.385167897],"iteration":123,"passed_time":0.09266220822,"remaining_time":0.1315205536},
{"learn":[3.382590094],"iteration":124,"passed_time":0.09340744547,"remaining_time":0.1307704237},
{"learn":[3.379558282],"iteration":125,"passed_time":0.09408948717,"remaining_time":0.1299331013},
{"learn":[3.378692223],"iteration":126,"passed_time":0.0947726407,"remaining_time":0.1290997389},
{"learn":[3.376338922],"iteration":127,"passed_time":0.09548094037,"remaining_time":0.1283025136},
{"learn":[3.373065146],"iteration":128,"passed_time":0.09622005659,"remaining_time":0.1275475169},
{"learn":[3.370391477],"iteration":129,"passed_time":0.09693712256,"remaining_time":0.1267639295},
{"learn":[3.368813829],"iteration":130,"passed_time":0.09762415341,"remaining_time":0.1259426101},
{"learn":[3.364306888],"iteration":131,"passed_time":0.09838208415,"remaining_time":0.1252135616},
{"learn":[3.359636545],"iteration":132,"passed_time":0.09909268805,"remaining_time":0.1244246534},
{"learn":[3.356664837],"iteration":133,"passed_time":0.0998427742,"remaining_time":0.1236858248},
{"learn":[3.355357774],"iteration":134,"passed_time":0.1005453634,"remaining_time":0.1228887775},
{"learn":[3.352132421],"iteration":135,"passed_time":0.1012723373,"remaining_time":0.1221225244},
{"learn":[3.349462591],"iteration":136,"passed_time":0.1019969167,"remaining_time":0.1213539958},
{"learn":[3.347170109],"iteration":137,"passed_time":0.102672967,"remaining_time":0.1205291351},
{"learn":[3.34402332],"iteration":138,"passed_time":0.1033969452,"remaining_time":0.1197619293},
{"learn":[3.342968597],"iteration":139,"passed_time":0.1040797381,"remaining_time":0.1189482721},
{"learn":[3.340172728],"iteration":140,"passed_time":0.1048249054,"remaining_time":0.1182068082},
{"learn":[3.336354962],"iteration":141,"passed_time":0.1055507974,"remaining_time":0.1174438449},
{"learn":[3.336146663],"iteration":142,"passed_time":0.1062189434,"remaining_time":0.1166180007},
{"learn":[3.333516128],"iteration":143,"passed_time":0.1069318413,"remaining_time":0.115842828},
{"learn":[3.331646097],"iteration":144,"passed_time":0.1076335689,"remaining_time":0.1150565736},
{"learn":[3.329106369],"iteration":145,"passed_time":0.1083298264,"remaining_time":0.1142657074},
{"learn":[3.326880237],"iteration":146,"passed_time":0.1090584536,"remaining_time":0.1135098191},
{"learn":[3.322073745],"iteration":147,"passed_time":0.1097881926,"remaining_time":0.1127554411},
{"learn":[3.320198863],"iteration":148,"passed_time":0.1105176511,"remaining_time":0.1120011095},
{"learn":[3.316841553],"iteration":149,"passed_time":0.1112432425,"remaining_time":0.1112432425},
{"learn":[3.314766181],"iteration":150,"passed_time":0.1119649668,"remaining_time":0.1104819872},
{"learn":[3.311789319],"iteration":151,"passed_time":0.1127182789,"remaining_time":0.1097520084},
{"learn":[3.311587168],"iteration":152,"passed_time":0.1133931172,"remaining_time":0.1089463283},
{"learn":[3.309760472],"iteration":153,"passed_time":0.1140811499,"remaining_time":0.1081548564},
{"learn":[3.306416985],"iteration":154,"passed_time":0.1148185327,"remaining_time":0.1074108854},
{"learn":[3.303346321],"iteration":155,"passed_time":0.1155575087,"remaining_time":0.1066684695},
{"learn":[3.300738668],"iteration":156,"passed_time":0.1162990694,"remaining_time":0.1059284517},
{"learn":[3.298498758],"iteration":157,"passed_time":0.1170046939,"remaining_time":0.1051561173},
{"learn":[3.296277247],"iteration":158,"passed_time":0.1177642276,"remaining_time":0.1044324283},
{"learn":[3.293748498],"iteration":159,"passed_time":0.1184933156,"remaining_time":0.1036816512},
{"learn":[3.291681865],"iteration":160,"passed_time":0.1192155707,"remaining_time":0.1029252443},
{"learn":[3.289153786],"iteration":161,"passed_time":0.1199285889,"remaining_time":0.1021613905},
{"learn":[3.287223426],"iteration":162,"passed_time":0.1206501431,"remaining_time":0.101405335},
{"learn":[3.286083055],"iteration":163,"passed_time":0.1213712765,"remaining_time":0.1006493512},
{"learn":[3.285905758],"iteration":164,"passed_time":0.1220501021,"remaining_time":0.09985917442},
{"learn":[3.284177143],"iteration":165,"passed_time":0.1227552658,"remaining_time":0.09909160009},
{"learn":[3.282590853],"iteration":166,"passed_time":0.1234647677,"remaining_time":0.09832822814},
{"learn":[3.280835094],"iteration":167,"passed_time":0.1241730273,"remaining_time":0.09756452142},
{"learn":[3.278791301],"iteration":168,"passed_time":0.1248867369,"remaining_time":0.09680569544},
{"learn":[3.275011765],"iteration":169,"passed_time":0.1255985728,"remaining_time":0.09604596745},
{"learn":[3.274846896],"iteration":170,"passed_time":0.1262543659,"remaining_time":0.09524452168},
{"learn":[3.272647573],"iteration":171,"passed_time":0.126979306,"remaining_time":0.09449622768},
{"learn":[3.270054618],"iteration":172,"passed_time":0.1277042963,"remaining_time":0.0937482406},
{"learn":[3.266772906],"iteration":173,"passed_time":0.1284582499,"remaining_time":0.09302149131},
{"learn":[3.264759223],"iteration":174,"passed_time":0.1292046194,"remaining_time":0.09228901388},
{"learn":[3.26344198],"iteration":175,"passed_time":0.1299067277,"remaining_time":0.09152519455},
{"learn":[3.2616094],"iteration":176,"passed_time":0.1306277908,"remaining_time":0.09077524448},
{"learn":[3.258585377],"iteration":177,"passed_time":0.1313094616,"remaining_time":0.08999861978},
{"learn":[3.25843916],"iteration":178,"passed_time":0.1319812543,"remaining_time":0.08921637863},
{"learn":[3.256615279],"iteration":179,"passed_time":0.1326903755,"remaining_time":0.08846025034},
{"learn":[3.252902945],"iteration":180,"passed_time":0.1333951287,"remaining_time":0.08770176969},
{"learn":[3.250534869],"iteration":181,"passed_time":0.1341215817,"remaining_time":0.08695794855},
{"learn":[3.247081382],"iteration":182,"passed_time":0.1348479345,"remaining_time":0.08621425318},
{"learn":[3.244618628],"iteration":183,"passed_time":0.1355743376,"remaining_time":0.08547077803},
{"learn":[3.242584849],"iteration":184,"passed_time":0.1363342119,"remaining_time":0.08474829387},
{"learn":[3.241762908],"iteration":185,"passed_time":0.1370050228,"remaining_time":0.0839708204},
{"learn":[3.239771714],"iteration":186,"passed_time":0.1377639455,"remaining_time":0.08324773179},
{"learn":[3.237775901],"iteration":187,"passed_time":0.1384815124,"remaining_time":0.08249962441},
{"learn":[3.234952562],"iteration":188,"passed_time":0.1392157495,"remaining_time":0.08176163064},
{"learn":[3.232790858],"iteration":189,"passed_time":0.1399449978,"remaining_time":0.08102078819},
{"learn":[3.231481858],"iteration":190,"passed_time":0.1406733142,"remaining_time":0.08027953532},
{"learn":[3.229560264],"iteration":191,"passed_time":0.1414151256,"remaining_time":0.07954600813},
{"learn":[3.226809472],"iteration":192,"passed_time":0.1421556546,"remaining_time":0.07881168414},
{"learn":[3.225074375],"iteration":193,"passed_time":0.142857693,"remaining_time":0.07805626523},
{"learn":[3.223078136],"iteration":194,"passed_time":0.1436027298,"remaining_time":0.07732454684},
{"learn":[3.221077676],"iteration":195,"passed_time":0.1443172908,"remaining_time":0.07657652165},
{"learn":[3.218472054],"iteration":196,"passed_time":0.1450455974,"remaining_time":0.075836023},
{"learn":[3.216094003],"iteration":197,"passed_time":0.1457847537,"remaining_time":0.07510123675},
{"learn":[3.214713975],"iteration":198,"passed_time":0.1465144228,"remaining_time":0.07436159146},
{"learn":[3.212158382],"iteration":199,"passed_time":0.1472736158,"remaining_time":0.07363680792},
{"learn":[3.210661059],"iteration":200,"passed_time":0.1479867341,"remaining_time":0.07288898846},
{"learn":[3.208512384],"iteration":201,"passed_time":0.148686308,"remaining_time":0.07213494151},
{"learn":[3.20689098],"iteration":202,"passed_time":0.1494020712,"remaining_time":0.07138916701},
{"learn":[3.205099911],"iteration":203,"passed_time":0.1501444832,"remaining_time":0.07065622741},
{"learn":[3.203234259],"iteration":204,"passed_time":0.1508681311,"remaining_time":0.06991449977},
{"learn":[3.201504635],"iteration":205,"passed_time":0.1515668331,"remaining_time":0.06916156464},
{"learn":[3.199395629],"iteration":206,"passed_time":0.1522808433,"remaining_time":0.06841603104},
{"learn":[3.197807494],"iteration":207,"passed_time":0.1530331539,"remaining_time":0.06768774116},
{"learn":[3.196317186],"iteration":208,"passed_time":0.1537416437,"remaining_time":0.06694014153},
{"learn":[3.194505048],"iteration":209,"passed_time":0.1544552932,"remaining_time":0.06619512567},
{"learn":[3.192785269],"iteration":210,"passed_time":0.1551595553,"remaining_time":0.06544644749},
{"learn":[3.191089942],"iteration":211,"passed_time":0.1558836439,"remaining_time":0.06470641824},
{"learn":[3.18818651],"iteration":212,"passed_time":0.1569903044,"remaining_time":0.06412280038},
{"learn":[3.186107845],"iteration":213,"passed_time":0.1577357923,"remaining_time":0.06338915017},
{"learn":[3.184296059],"iteration":214,"passed_time":0.1584329515,"remaining_time":0.06263628316},
{"learn":[3.182641785],"iteration":215,"passed_time":0.1591739009,"remaining_time":0.06190096146},
{"learn":[3.181334299],"iteration":216,"passed_time":0.1598961965,"remaining_time":0.06115845302},
{"learn":[3.179429454],"iteration":217,"passed_time":0.1606017208,"remaining_time":0.0604098216},
{"learn":[3.176774361],"iteration":218,"passed_time":0.1613538609,"remaining_time":0.05967882528},
{"learn":[3.173618583],"iteration":219,"passed_time":0.1620840007,"remaining_time":0.05893963662},
{"learn":[3.172129171],"iteration":220,"passed_time":0.1628059556,"remaining_time":0.05819760405},
{"learn":[3.170711804],"iteration":221,"passed_time":0.1635446511,"remaining_time":0.05746163416},
{"learn":[3.169058547],"iteration":222,"passed_time":0.1642747908,"remaining_time":0.05672268562},
{"learn":[3.167840655],"iteration":223,"passed_time":0.1649854548,"remaining_time":0.05597720789},
{"learn":[3.165528388],"iteration":224,"passed_time":0.1656915905,"remaining_time":0.05523053018},
{"learn":[3.162417697],"iteration":225,"passed_time":0.1664173623,"remaining_time":0.05449064074},
{"learn":[3.161022215],"iteration":226,"passed_time":0.1671639121,"remaining_time":0.05375755765},
{"learn":[3.159273264],"iteration":227,"passed_time":0.1678751572,"remaining_time":0.05301320754},
{"learn":[3.157195215],"iteration":228,"passed_time":0.1686002477,"remaining_time":0.05227343924},
{"learn":[3.155963877],"iteration":229,"passed_time":0.1693189064,"remaining_time":0.05153184107},
{"learn":[3.154357155],"iteration":230,"passed_time":0.1700468822,"remaining_time":0.05079322454},
{"learn":[3.152594562],"iteration":231,"passed_time":0.1707708404,"remaining_time":0.05005352217},
{"learn":[3.150154083],"iteration":232,"passed_time":0.1715299332,"remaining_time":0.04932405805},
{"learn":[3.147859977],"iteration":233,"passed_time":0.1722697107,"remaining_time":0.04858889275},
{"learn":[3.146737387],"iteration":234,"passed_time":0.1729738828,"remaining_time":0.04784383991},
{"learn":[3.144408846],"iteration":235,"passed_time":0.173688474,"remaining_time":0.04710195905},
{"learn":[3.14380911],"iteration":236,"passed_time":0.1743786306,"remaining_time":0.04635381319},
{"learn":[3.142734172],"iteration":237,"passed_time":0.1751054041,"remaining_time":0.04561569352},
{"learn":[3.142615484],"iteration":238,"passed_time":0.1757962718,"remaining_time":0.04486850453},
{"learn":[3.14126394],"iteration":239,"passed_time":0.1764957054,"remaining_time":0.04412392636},
{"learn":[3.138617662],"iteration":240,"passed_time":0.1772338497,"remaining_time":0.04338919971},
{"learn":[3.137138434],"iteration":241,"passed_time":0.1779760417,"remaining_time":0.04265541496},
{"learn":[3.136205186],"iteration":242,"passed_time":0.1787090067,"remaining_time":0.04191939663},
{"learn":[3.134951712],"iteration":243,"passed_time":0.1794569693,"remaining_time":0.04118684542},
{"learn":[3.133964591],"iteration":244,"passed_time":0.1801645677,"remaining_time":0.04044510704},
{"learn":[3.131830376],"iteration":245,"passed_time":0.180895679,"remaining_time":0.03970880759},
{"learn":[3.128916906],"iteration":246,"passed_time":0.1815987593,"remaining_time":0.03896653541},
{"learn":[3.126287773],"iteration":247,"passed_time":0.1823624006,"remaining_time":0.03823727754},
{"learn":[3.12418179],"iteration":248,"passed_time":0.183056414,"remaining_time":0.03749348239},
{"learn":[3.122201043],"iteration":249,"passed_time":0.1837799016,"remaining_time":0.03675598031},
{"learn":[3.121060707],"iteration":250,"passed_time":0.1844817093,"remaining_time":0.0360143576},
{"learn":[3.118520294],"iteration":251,"passed_time":0.185253766,"remaining_time":0.03528643162},
{"learn":[3.116687601],"iteration":252,"passed_time":0.185981772,"remaining_time":0.03454997346},
{"learn":[3.115752975],"iteration":253,"passed_time":0.1867266687,"remaining_time":0.03381664078},
{"learn":[3.114092876],"iteration":254,"passed_time":0.1874572995,"remaining_time":0.03308069991},
{"learn":[3.113980101],"iteration":255,"passed_time":0.1881368665,"remaining_time":0.03233602392},
{"learn":[3.112407011],"iteration":256,"passed_time":0.1888768344,"remaining_time":0.03160196063},
{"learn":[3.110794229],"iteration":257,"passed_time":0.1896323305,"remaining_time":0.03087037939},
{"learn":[3.107988572],"iteration":258,"passed_time":0.1904106988,"remaining_time":0.03014223417},
{"learn":[3.105735055],"iteration":259,"passed_time":0.1911519291,"remaining_time":0.02940798909},
{"learn":[3.103243261],"iteration":260,"passed_time":0.1918796043,"remaining_time":0.02867166501},
{"learn":[3.1016522],"iteration":261,"passed_time":0.1925973511,"remaining_time":0.02793396695},
{"learn":[3.100184449],"iteration":262,"passed_time":0.1933303561,"remaining_time":0.02719856721},
{"learn":[3.100080235],"iteration":263,"passed_time":0.1940275955,"remaining_time":0.02645830847},
{"learn":[3.097426129],"iteration":264,"passed_time":0.19479306,"remaining_time":0.02572738529},
{"learn":[3.095994566],"iteration":265,"passed_time":0.1955000475,"remaining_time":0.02498872788},
{"learn":[3.092567163],"iteration":266,"passed_time":0.1962328922,"remaining_time":0.02425350353},
{"learn":[3.091156744],"iteration":267,"passed_time":0.1969632123,"remaining_time":0.0235179955},
{"learn":[3.089234182],"iteration":268,"passed_time":0.1976828528,"remaining_time":0.0227812953},
{"learn":[3.088097829],"iteration":269,"passed_time":0.1983862537,"remaining_time":0.02204291708},
{"learn":[3.086503007],"iteration":270,"passed_time":0.1991377424,"remaining_time":0.02130994291},
{"learn":[3.08527835],"iteration":271,"passed_time":0.1998830099,"remaining_time":0.0205761922},
{"learn":[3.083746025],"iteration":272,"passed_time":0.2005845572,"remaining_time":0.01983803313},
{"learn":[3.081869302],"iteration":273,"passed_time":0.2013105191,"remaining_time":0.01910245801},
{"learn":[3.079381432],"iteration":274,"passed_time":0.2020332051,"remaining_time":0.01836665501},
{"learn":[3.079285998],"iteration":275,"passed_time":0.2027183022,"remaining_time":0.01762767846},
{"learn":[3.077542262],"iteration":276,"passed_time":0.2034173249,"remaining_time":0.01689024719},
{"learn":[3.076253549],"iteration":277,"passed_time":0.2040936561,"remaining_time":0.01615129653},
{"learn":[3.073698881],"iteration":278,"passed_time":0.2048286448,"remaining_time":0.01541720982},
{"learn":[3.072815845],"iteration":279,"passed_time":0.2055487162,"remaining_time":0.01468205116},
{"learn":[3.071534651],"iteration":280,"passed_time":0.2062663931,"remaining_time":0.01394683797},
{"learn":[3.070264692],"iteration":281,"passed_time":0.2069555376,"remaining_time":0.01320992793},
{"learn":[3.068403041],"iteration":282,"passed_time":0.2077187982,"remaining_time":0.01247780766},
{"learn":[3.067007343],"iteration":283,"passed_time":0.2084484472,"remaining_time":0.01174357449},
{"learn":[3.065270007],"iteration":284,"passed_time":0.2091855197,"remaining_time":0.01100976419},
{"learn":[3.06363147],"iteration":285,"passed_time":0.2098937094,"remaining_time":0.01027451724},
{"learn":[3.062709676],"iteration":286,"passed_time":0.2106083709,"remaining_time":0.009539751992},
{"learn":[3.060941192],"iteration":287,"passed_time":0.2113330508,"remaining_time":0.008805543785},
{"learn":[3.058393972],"iteration":288,"passed_time":0.212057981,"remaining_time":0.008071411043},
{"learn":[3.057256737],"iteration":289,"passed_time":0.2127580157,"remaining_time":0.007336483302},
{"learn":[3.054077113],"iteration":290,"passed_time":0.2135479252,"remaining_time":0.006604575005},
{"learn":[3.052149913],"iteration":291,"passed_time":0.2142731862,"remaining_time":0.005870498251},
{"learn":[3.05114874],"iteration":292,"passed_time":0.214997916,"remaining_time":0.005136468983},
{"learn":[3.04991885],"iteration":293,"passed_time":0.2157036309,"remaining_time":0.004402114917},
{"learn":[3.047793579],"iteration":294,"passed_time":0.2164534566,"remaining_time":0.003668702654},
{"learn":[3.046726759],"iteration":295,"passed_time":0.217175892,"remaining_time":0.002934809351},
{"learn":[3.045284185],"iteration":296,"passed_time":0.2178864059,"remaining_time":0.002200872787},
{"learn":[3.043343634],"iteration":297,"passed_time":0.2186226369,"remaining_time":0.001467266019},
{"learn":[3.042326266],"iteration":298,"passed_time":0.2193379997,"remaining_time":0.0007335719053},
{"learn":[3.040353573],"iteration":299,"passed_time":0.2200977436,"remaining_time":0}
]}