{
"meta":{"test_sets":[],"test_metrics":[],"learn_metrics":[{"best_value":"Min","name":"QueryRMSE"}],"launch_mode":"Train","parameters":"","iteration_count":300,"learn_sets":["learn"],"name":"experiment"},
"iterations":[
{"learn":[5.513728811],"iteration":0,"passed_time":0.0008348985998,"remaining_time":0.2496346813},
{"learn":[5.300698237],"iteration":1,"passed_time":0.001570873328,"remaining_time":0.2340601259},
{"learn":[5.117587747],"iteration":2,"passed_time":0.002315834927,"remaining_time":0.2292676578},
{"learn":[4.960853105],"iteration":3,"passed_time":0.003091032602,"remaining_time":0.2287364126},
{"learn":[4.840234589],"iteration":4,"passed_time":0.003859567717,"remaining_time":0.2277144953},
{"learn":[4.712389572],"iteration":5,"passed_time":0.004593398469,"remaining_time":0.225076525},
{"learn":[4.615246351],"iteration":6,"passed_time":0.005366472205,"remaining_time":0.2246251937},
{"learn":[4.529233821],"iteration":7,"passed_time":0.006108167747,"remaining_time":0.2229481228},
{"learn":[4.445058272],"iteration":8,"passed_time":0.006860543096,"remaining_time":0.2218242268},
{"learn":[4.366624791],"iteration":9,"passed_time":0.007597720054,"remaining_time":0.2203338816},
{"learn":[4.304269382],"iteration":10,"passed_time":0.008298179119,"remaining_time":0.2180157968},
{"learn":[4.240447412],"iteration":11,"passed_time":0.009034685036,"remaining_time":0.2168324409},
{"learn":[4.185108921],"iteration":12,"passed_time":0.009775919724,"remaining_time":0.2158222277},
{"learn":[4.143281359],"iteration":13,"passed_time":0.01048084708,"remaining_time":0.2141087331},
{"learn":[4.102989876],"iteration":14,"passed_time":0.01123893302,"remaining_time":0.2135397273},
{"learn":[4.067831184],"iteration":15,"passed_time":0.01198211131,"remaining_time":0.2126824757},
{"learn":[4.034308684],"iteration":16,"passed_time":0.01271053244,"remaining_time":0.2115929811},
{"learn":[4.009190385],"iteration":17,"passed_time":0.01344411293,"remaining_time":0.2106244359},
{"learn":[3.982040912],"iteration":18,"passed_time":0.01415980023,"remaining_time":0.2094159929},
{"learn":[3.960374395],"iteration":19,"passed_time":0.01489817983,"remaining_time":0.2085745176},
{"learn":[3.935901836],"iteration":20,"passed_time":0.01565741811,"remaining_time":0.2080199835},
{"learn":[3.920326998],"iteration":21,"passed_time":0.01640751904,"remaining_time":0.2073313769},
{"learn":[3.899762536],"iteration":22,"passed_time":0.01714524722,"remaining_time":0.2064884122},
{"learn":[3.884484105],"iteration":23,"passed_time":0.01788413756,"remaining_time":0.205667582},
{"learn":[3.867148915],"iteration":24,"passed_time":0.01858438603,"remaining_time":0.2044282464},
{"learn":[3.855963473],"iteration":25,"passed_time":0.01934060852,"remaining_time":0.203820259},
{"learn":[3.844246847],"iteration":26,"passed_time":0.02006354928,"remaining_time":0.202864776},
{"learn":[3.827692035],"iteration":27,"passed_time":0.02078967594,"remaining_time":0.201956852},
{"learn":[3.816110382],"iteration":28,"passed_time":0.02153686167,"remaining_time":0.201258259},
{"learn":[3.805578573],"iteration":29,"passed_time":0.0222903591,"remaining_time":0.2006132319},
{"learn":[3.795532562],"iteration":30,"passed_time":0.0230212448,"remaining_time":0.1997649952},
{"learn":[3.784817268],"iteration":31,"passed_time":0.02375892268,"remaining_time":0.1989809775},
{"learn":[3.775684476],"iteration":32,"passed_time":0.02450763123,"remaining_time":0.1982890163},
{"learn":[3.76493924],"iteration":33,"passed_time":0.02523805608,"remaining_time":0.197450674},
{"learn":[3.755797259],"iteration":34,"passed_time":0.02596712821,"remaining_time":0.1966082564},
{"learn":[3.747549142],"iteration":35,"passed_time":0.02667508117,"remaining_time":0.1956172619},
{"learn":[3.740131889],"iteration":36,"passed_time":0.0274006468,"remaining_time":0.1947667597},
{"learn":[3.733339221],"iteration":37,"passed_time":0.02812148366,"remaining_time":0.1938902294},
{"learn":[3.72402179],"iteration":38,"passed_time":0.02887294711,"remaining_time":0.193226646},
{"learn":[3.716666309],"iteration":39,"passed_time":0.02956896774,"remaining_time":0.1921982903},
{"learn":[3.711679034],"iteration":40,"passed_time":0.0302816597,"remaining_time":0.19129146},
{"learn":[3.706224944],"iteration":41,"passed_time":0.03100787633,"remaining_time":0.1904769546},
{"learn":[3.701206372],"iteration":42,"passed_time":0.03173194939,"remaining_time":0.189653744},
{"learn":[3.697335382],"iteration":43,"passed_time":0.03245998981,"remaining_time":0.1888581225},
{"learn":[3.688445213],"iteration":44,"passed_time":0.03316475687,"remaining_time":0.1879336222},
{"learn":[3.681906839],"iteration":45,"passed_time":0.03388602432,"remaining_time":0.1871097865},
{"learn":[3.676274937],"iteration":46,"passed_time":0.03462090723,"remaining_time":0.186363607},
{"learn":[3.671870581],"iteration":47,"passed_time":0.03534532051,"remaining_time":0.1855629327},
{"learn":[3.667931311],"iteration":48,"passed_time":0.03608312885,"remaining_time":0.1848339865},
{"learn":[3.662401014],"iteration":49,"passed_time":0.03677857862,"remaining_time":0.1838928931},
{"learn":[3.655342049],"iteration":50,"passed_time":0.03748830508,"remaining_time":0.1830311366},
{"learn":[3.65330614],"iteration":51,"passed_time":0.03815129465,"remaining_time":0.1819523283},
{"learn":[3.64923407],"iteration":52,"passed_time":0.03883698633,"remaining_time":0.1809950118},
{"learn":[3.644710428],"iteration":53,"passed_time":0.03953429956,"remaining_time":0.180100698},
{"learn":[3.641335141],"iteration":54,"passed_time":0.0402269241,"remaining_time":0.1791926619},
{"learn":[3.633994918],"iteration":55,"passed_time":0.04096134615,"remaining_time":0.1784744368},
{"learn":[3.632151083],"iteration":56,"passed_time":0.04164951262,"remaining_time":0.1775584485},
{"learn":[3.627754002],"iteration":57,"passed_time":0.04237868494,"remaining_time":0.1768214096},
{"learn":[3.623900526],"iteration":58,"passed_time":0.04306250335,"remaining_time":0.1758993781},
{"learn":[3.618277458],"iteration":59,"passed_time":0.04376976523,"remaining_time":0.1750790609},
{"learn":[3.613951621],"iteration":60,"passed_time":0.04450409732,"remaining_time":0.1743685125},
{"learn":[3.60926162],"iteration":61,"passed_time":0.04517922942,"remaining_time":0.1734299452},
{"learn":[3.605344654],"iteration":62,"passed_time":0.04589933471,"remaining_time":0.1726689258},
{"learn":[3.600341086],"iteration":63,"passed_time":0.04659240007,"remaining_time":0.1718094752},
{"learn":[3.597248898],"iteration":64,"passed_time":0.04731096291,"remaining_time":0.1710473274},
{"learn":[3.594376989],"iteration":65,"passed_time":0.04803477549,"remaining_time":0.1703051131},
{"learn":[3.592585689],"iteration":66,"passed_time":0.04874440135,"remaining_time":0.1695141122},
{"learn":[3.588886264],"iteration":67,"passed_time":0.04945865621,"remaining_time":0.1687412976},
{"learn":[3.584225483],"iteration":68,"passed_time":0.05015324438,"remaining_time":0.1679043399},
{"learn":[3.577430264],"iteration":69,"passed_time":0.05083503904,"remaining_time":0.167029414},
{"learn":[3.574405013],"iteration":70,"passed_time":0.05152853499,"remaining_time":0.1661976692},
{"learn":[3.570809834],"iteration":71,"passed_time":0.05226252644,"remaining_time":0.1654980004},
{"learn":[3.564888115],"iteration":72,"passed_time":0.05301278767,"remaining_time":0.1648479836},
{"learn":[3.560166451],"iteration":73,"passed_time":0.05371029105,"remaining_time":0.1640341321},
{"learn":[3.556502214],"iteration":74,"passed_time":0.05443017594,"remaining_time":0.1632905278},
{"learn":[3.554044374],"iteration":75,"passed_time":0.0551250246,"remaining_time":0.1624737567},
{"learn":[3.550305233],"iteration":76,"passed_time":0.05581891147,"remaining_time":0.161657367},
{"learn":[3.545666373],"iteration":77,"passed_time":0.05650646661,"remaining_time":0.1608260973},
{"learn":[3.542516906],"iteration":78,"passed_time":0.05721038188,"remaining_time":0.1600442328},
{"learn":[3.54043876],"iteration":79,"passed_time":0.05792149049,"remaining_time":0.1592840988},
{"learn":[3.536472051],"iteration":80,"passed_time":0.05863228873,"remaining_time":0.1585243362},
{"learn":[3.53238018],"iteration":81,"passed_time":0.05931621714,"remaining_time":0.1576943334},
{"learn":[3.530176845],"iteration":82,"passed_time":0.0600040029,"remaining_time":0.1568779353},
{"learn":[3.525939693],"iteration":83,"passed_time":0.06071512174,"remaining_time":0.1561245988},
{"learn":[3.522741669],"iteration":84,"passed_time":0.06139284885,"remaining_time":0.1552877941},
{"learn":[3.520431888],"iteration":85,"passed_time":0.06209413966,"remaining_time":0.1545133243},
{"learn":[3.516554877],"iteration":86,"passed_time":0.06280395608,"remaining_time":0.1537614097},
{"learn":[3.512607631],"iteration":87,"passed_time":0.06359033449,"remaining_time":0.1531948967},
{"learn":[3.510020967],"iteration":88,"passed_time":0.06429127445,"remaining_time":0.1524208866},
{"learn":[3.505360719],"iteration":89,"passed_time":0.06500591001,"remaining_time":0.1516804567},
{"learn":[3.503792895],"iteration":90,"passed_time":0.06571226,"remaining_time":0.1509215642},
{"learn":[3.499445685],"iteration":91,"passed_time":0.06644386663,"remaining_time":0.1502209159},
{"learn":[3.497160459],"iteration":92,"passed_time":0.06711358869,"remaining_time":0.1493818587},
{"learn":[3.491533569],"iteration":93,"passed_time":0.0678283641,"remaining_time":0.1486451383},
{"learn":[3.48712542],"iteration":94,"passed_time":0.0685463659,"remaining_time":0.1479158422},
{"learn":[3.484261631],"iteration":95,"passed_time":0.06927713097,"remaining_time":0.1472139033},
{"learn":[3.480669646],"iteration":96,"passed_time":0.06998364126,"remaining_time":0.1464606101},
{"learn":[3.475866169],"iteration":97,"passed_time":0.0706876972,"remaining_time":0.1457032126},
{"learn":[3.473149013],"iteration":98,"passed_time":0.0714101771,"remaining_time":0.144984299},
{"learn":[3.468235915],"iteration":99,"passed_time":0.07217190981,"remaining_time":0.1443438196},
{"learn":[3.464423965],"iteration":100,"passed_time":0.07295901937,"remaining_time":0.1437509392},
{"learn":[3.461669379],"iteration":101,"passed_time":0.07367520761,"remaining_time":0.1430165795},
{"learn":[3.458617803],"iteration":102,"passed_time":0.07437763031,"remaining_time":0.1422562444},
{"learn":[3.45677238],"iteration":103,"passed_time":0.07508301852,"remaining_time":0.1415026118},
{"learn":[3.453660668],"iteration":104,"passed_time":0.07578546126,"remaining_time":0.1407444281},
{"learn":[3.448919792],"iteration":105,"passed_time":0.07651463358,"remaining_time":0.1400362162},
{"learn":[3.447059566],"iteration":106,"passed_time":0.07721493235,"remaining_time":0.1392755322},
{"learn":[3.443471078],"iteration":107,"passed_time":0.07794797184,"remaining_time":0.1385741722},
{"learn":[3.440044413],"iteration":108,"passed_time":0.07862397534,"remaining_time":0.1377722871},
{"learn":[3.435070758],"iteration":109,"passed_time":0.07935079309,"remaining_time":0.1370604608},
{"learn":[3.430107253],"iteration":110,"passed_time":0.08010147509,"remaining_time":0.1363889981},
{"learn":[3.427146486],"iteration":111,"passed_time":0.08081594013,"remaining_time":0.1356553281},
{"learn":[3.424287516],"iteration":112,"passed_time":0.08150167189,"remaining_time":0.1348744482},
{"learn":[3.420932511],"iteration":113,"passed_time":0.08223626446,"remaining_time":0.1341749578},
{"learn":[3.417404749],"iteration":114,"passed_time":0.08295392522,"remaining_time":0.1334476188},
{"learn":[3.413584269],"iteration":115,"passed_time":0.08369497958,"remaining_time":0.1327575538},
{"learn":[3.411041483],"iteration":116,"passed_time":0.08441336168,"remaining_time":0.1320311554},
{"learn":[3.409015145],"iteration":117,"passed_time":0.0851409208,"remaining_time":0.1313190473},
{"learn":[3.406004922],"iteration":118,"passed_time":0.08586661646,"remaining_time":0.1306038452},
{"learn":[3.403591454],"iteration":119,"passed_time":0.08655902059,"remaining_time":0.1298385309},
{"learn":[3.401467497],"iteration":120,"passed_time":0.0872492607,"remaining_time":0.1290712204},
{"learn":[3.399328498],"iteration":121,"passed_time":0.08797442559,"remaining_time":0.1283561291},
{"learn":[3.396365398],"iteration":122,"passed_time":0.08866624864,"remaining_time":0.1275928944},
{"learn":[3.391950474],"iteration":123,"passed_time":0.08939068196,"remaining_time":0.126877097},
{"learn":[3.389751142],"iteration":124,"passed_time":0.09007921891,"remaining_time":0.1261109065},
{"learn":[3.389057025],"iteration":125,"passed_time":0.0907730056,"remaining_time":0.1253531982},
{"learn":[3.38720325],"iteration":126,"passed_time":0.09145269636,"remaining_time":0.124577295},
{"learn":[3.383359448],"iteration":127,"passed_time":0.09214541086,"remaining_time":0.1238203958},
{"learn":[3.379491978],"iteration":128,"passed_time":0.09285586846,"remaining_time":0.1230880117},
{"learn":[3.377066808],"iteration":129,"passed_time":0.09356328042,"remaining_time":0.1223519821},
{"learn":[3.374114685],"iteration":130,"passed_time":0.09426010254,"remaining_time":0.1216027277},
{"learn":[3.371897459],"iteration":131,"passed_time":0.09495973027,"remaining_time":0.1208578385},
{"learn":[3.367306278],"iteration":132,"passed_time":0.09567868363,"remaining_time":0.120137896},
{"learn":[3.364850934],"iteration":133,"passed_time":0.09635769271,"remaining_time":0.119368485},
{"learn":[3.360544763],"iteration":134,"passed_time":0.09704717141,"remaining_time":0.1186132095},
{"learn":[3.356988769],"iteration":135,"passed_time":0.09778062146,"remaining_time":0.1179119259},
{"learn":[3.3543715],"iteration":136,"passed_time":0.09847652187,"remaining_time":0.1171654968},
{"learn":[3.35077943],"iteration":137,"passed_time":0.09918759081,"remaining_time":0.1164376066},
{"learn":[3.347205936],"iteration":138,"passed_time":0.09994202018,"remaining_time":0.1157601816},
{"learn":[3.344912928],"iteration":139,"passed_time":0.1006356965,"remaining_time":0.1150122245},
{"learn":[3.342427046],"iteration":140,"passed_time":0.1013332301,"remaining_time":0.1142693871},
{"learn":[3.341326009],"iteration":141,"passed_time":0.102024843,"remaining_time":0.1135205999},
{"learn":[3.340332614],"iteration":142,"passed_time":0.1026756001,"remaining_time":0.1127277567},
{"learn":[3.338532668],"iteration":143,"passed_time":0.1033653294,"remaining_time":0.1119791069},
{"learn":[3.334763402],"iteration":144,"passed_time":0.104101635,"remaining_time":0.1112810581},
{"learn":[3.332383104],"iteration":145,"passed_time":0.1048210492,"remaining_time":0.1105646683},
{"learn":[3.330286641],"iteration":146,"passed_time":0.1054969124,"remaining_time":0.1098029089},
{"learn":[3.328207889],"iteration":147,"passed_time":0.1061962294,"remaining_time":0.1090663977},
{"learn":[3.325313199],"iteration":148,"passed_time":0.1068927309,"remaining_time":0.1083275327},
{"learn":[3.321727251],"iteration":149,"passed_time":0.1076036894,"remaining_time":0.1076036894},
{"learn":[3.318864554],"iteration":150,"passed_time":0.1083188157,"remaining_time":0.1068841294},
{"learn":[3.317945334],"iteration":151,"passed_time":0.1089875559,"remaining_time":0.1061194624},
{"learn":[3.315177521],"iteration":152,"passed_time":0.1096840276,"remaining_time":0.1053826932},
{"learn":[3.312727903],"iteration":153,"passed_time":0.1103647803,"remaining_time":0.104631545},
{"learn":[3.310976411],"iteration":154,"passed_time":0.1110826116,"remaining_time":0.1039159915},
{"learn":[3.309261638],"iteration":155,"passed_time":0.1117699766,"remaining_time":0.1031722861},
{"learn":[3.306470655],"iteration":156,"passed_time":0.1124993791,"remaining_time":0.1024675874},
{"learn":[3.302700026],"iteration":157,"passed_time":0.1132005596,"remaining_time":0.1017372117},
{"learn":[3.300933367],"iteration":158,"passed_time":0.1139071201,"remaining_time":0.1010119745},
{"learn":[3.29853779],"iteration":159,"passed_time":0.1146085111,"remaining_time":0.1002824472},
{"learn":[3.29646198],"iteration":160,"passed_time":0.1153234873,"remaining_time":0.09956499838},
{"learn":[3.294423405],"iteration":161,"passed_time":0.1160038291,"remaining_time":0.09881807663},
{"learn":[3.291257168],"iteration":162,"passed_time":0.116745705,"remaining_time":0.09812369067},
{"learn":[3.289565039],"iteration":163,"passed_time":0.1174529063,"remaining_time":0.0973999711},
{"learn":[3.286988652],"iteration":164,"passed_time":0.1181483864,"remaining_time":0.09666686157},
{"learn":[3.283607315],"iteration":165,"passed_time":0.1188317439,"remaining_time":0.09592441979},
{"learn":[3.281249167],"iteration":166,"passed_time":0.1195186076,"remaining_time":0.09518547788},
{"learn":[3.279011897],"iteration":167,"passed_time":0.1201959736,"remaining_time":0.09443969354},
{"learn":[3.277016109],"iteration":168,"passed_time":0.1208747925,"remaining_time":0.09369584509},
{"learn":[3.276850837],"iteration":169,"passed_time":0.1215555551,"remaining_time":0.09295424799},
{"learn":[3.275603496],"iteration":170,"passed_time":0.1222316089,"remaining_time":0.0922098102},
{"learn":[3.273080284],"iteration":171,"passed_time":0.1229473461,"remaining_time":0.09149569939},
{"learn":[3.271417266],"iteration":172,"passed_time":0.1235976722,"remaining_time":0.09073355123},
{"learn":[3.267649858],"iteration":173,"passed_time":0.1243362619,"remaining_time":0.09003660347},
{"learn":[3.26538495],"iteration":174,"passed_time":0.1250235967,"remaining_time":0.08930256904},
{"learn":[3.263669198],"iteration":175,"passed_time":0.1257300366,"remaining_time":0.08858252579},
{"learn":[3.263514548],"iteration":176,"passed_time":0.126375674,"remaining_time":0.08782038363},
{"learn":[3.261217328],"iteration":177,"passed_time":0.1270668358,"remaining_time":0.08709075265},
{"learn":[3.258832757],"iteration":178,"passed_time":0.1277855487,"remaining_time":0.08638017541},
{"learn":[3.258271552],"iteration":179,"passed_time":0.1284327192,"remaining_time":0.08562181279},
{"learn":[3.255700318],"iteration":180,"passed_time":0.12917189,"remaining_time":0.08492516528},
{"learn":[3.254536013],"iteration":181,"passed_time":0.1298794222,"remaining_time":0.08420753749},
{"learn":[3.252875427],"iteration":182,"passed_time":0.1305718063,"remaining_time":0.08348033519},
{"learn":[3.24963858],"iteration":183,"passed_time":0.1312614253,"remaining_time":0.08275176811},
{"learn":[3.247471304],"iteration":184,"passed_time":0.1319753996,"remaining_time":0.08203876192},
{"learn":[3.245854033],"iteration":185,"passed_time":0.1326632954,"remaining_time":0.08130976169},
{"learn":[3.242991962],"iteration":186,"passed_time":0.1333816775,"remaining_time":0.08059962329},
{"learn":[3.239876596],"iteration":187,"passed_time":0.1340933173,"remaining_time":0.07988538051},
{"learn":[3.238910471],"iteration":188,"passed_time":0.1347624685,"remaining_time":0.07914621165},
{"learn":[3.234742502],"iteration":189,"passed_time":0.1354561452,"remaining_time":0.07842197879},
{"learn":[3.231950985],"iteration":190,"passed_time":0.1361806386,"remaining_time":0.0777156524},
{"learn":[3.230557105],"iteration":191,"passed_time":0.1368658294,"remaining_time":0.07698702902},
{"learn":[3.22749152],"iteration":192,"passed_time":0.1375410113,"remaining_time":0.07625330681},
{"learn":[3.225849465],"iteration":193,"passed_time":0.1382129076,"remaining_time":0.07551839284},
{"learn":[3.223766507],"iteration":194,"passed_time":0.138904911,"remaining_time":0.07479495209},
{"learn":[3.221946107],"iteration":195,"passed_time":0.1395829485,"remaining_time":0.07406442166},
{"learn":[3.219442036],"iteration":196,"passed_time":0.1402942579,"remaining_time":0.07335182012},
{"learn":[3.219313352],"iteration":197,"passed_time":0.140945686,"remaining_time":0.07260838372},
{"learn":[3.21670861],"iteration":198,"passed_time":0.1416532383,"remaining_time":0.0718943571},
{"learn":[3.214096044],"iteration":199,"passed_time":0.1423395912,"remaining_time":0.07116979558},
{"learn":[3.212506845],"iteration":200,"passed_time":0.1430073095,"remaining_time":0.07043643602},
{"learn":[3.210747269],"iteration":201,"passed_time":0.1436879416,"remaining_time":0.06970999147},
{"learn":[3.20828573],"iteration":202,"passed_time":0.1443889417,"remaining_time":0.06899373075},
{"learn":[3.206103321],"iteration":203,"passed_time":0.1450799232,"remaining_time":0.06827290501},
{"learn":[3.203389908],"iteration":204,"passed_time":0.1457577901,"remaining_time":0.06754629298},
{"learn":[3.20100416],"iteration":205,"passed_time":0.1464558046,"remaining_time":0.06682934775},
{"learn":[3.199219258],"iteration":206,"passed_time":0.1471319386,"remaining_time":0.06610275502},
{"learn":[3.198278298],"iteration":207,"passed_time":0.1477768747,"remaining_time":0.06536284842},
{"learn":[3.195825538],"iteration":208,"passed_time":0.1484801189,"remaining_time":0.06464923838},
{"learn":[3.193867248],"iteration":209,"passed_time":0.1491850565,"remaining_time":0.06393645278},
{"learn":[3.190637883],"iteration":210,"passed_time":0.1498969969,"remaining_time":0.06322669536},
{"learn":[3.189325108],"iteration":211,"passed_time":0.1505697045,"remaining_time":0.06250063204},
{"learn":[3.187538381],"iteration":212,"passed_time":0.151277457,"remaining_time":0.06178938386},
{"learn":[3.185745741],"iteration":213,"passed_time":0.1519568068,"remaining_time":0.06106675412},
{"learn":[3.184281839],"iteration":214,"passed_time":0.1526523265,"remaining_time":0.06035091976},
{"learn":[3.182996137],"iteration":215,"passed_time":0.1533524048,"remaining_time":0.05963704632},
{"learn":[3.181030876],"iteration":216,"passed_time":0.1540597967,"remaining_time":0.05892609737},
{"learn":[3.179178433],"iteration":217,"passed_time":0.1547470714,"remaining_time":0.058207614},
{"learn":[3.176372954],"iteration":218,"passed_time":0.1554379428,"remaining_time":0.05749074598},
{"learn":[3.174303999],"iteration":219,"passed_time":0.1561663337,"remaining_time":0.05678775771},
{"learn":[3.171765308],"iteration":220,"passed_time":0.1568871505,"remaining_time":0.05608183209},
{"learn":[3.169974608],"iteration":221,"passed_time":0.1575880402,"remaining_time":0.05536877088},
{"learn":[3.168524042],"iteration":222,"passed_time":0.1582451789,"remaining_time":0.054640712},
{"learn":[3.166084708],"iteration":223,"passed_time":0.1589496152,"remaining_time":0.05392933371},
{"learn":[3.164551356],"iteration":224,"passed_time":0.1596362784,"remaining_time":0.05321209281},
{"learn":[3.161487927],"iteration":225,"passed_time":0.1603196761,"remaining_time":0.05249405322},
{"learn":[3.159743529],"iteration":226,"passed_time":0.1610593078,"remaining_time":0.05179440294},
{"learn":[3.158213566],"iteration":227,"passed_time":0.1617623618,"remaining_time":0.05108285111},
{"learn":[3.155558775],"iteration":228,"passed_time":0.1624878874,"remaining_time":0.05037834064},
{"learn":[3.154115102],"iteration":229,"passed_time":0.1631894587,"remaining_time":0.04966635701},
{"learn":[3.152390291],"iteration":230,"passed_time":0.1639257945,"remaining_time":0.04896484772},
{"learn":[3.150692732],"iteration":231,"passed_time":0.1646245402,"remaining_time":0.04825202041},
{"learn":[3.148839171],"iteration":232,"passed_time":0.1653254,"remaining_time":0.0475399219},
{"learn":[3.148726234],"iteration":233,"passed_time":0.1659401904,"remaining_time":0.04680364345},
{"learn":[3.146694755],"iteration":234,"passed_time":0.1666162544,"remaining_time":0.04608534698},
{"learn":[3.145301552],"iteration":235,"passed_time":0.1673043305,"remaining_time":0.04537066591},
{"learn":[3.142923489],"iteration":236,"passed_time":0.1679494269,"remaining_time":0.04464478438},
{"learn":[3.141316635],"iteration":237,"passed_time":0.1686436847,"remaining_time":0.04393238845},
{"learn":[3.140069408],"iteration":238,"passed_time":0.1693149496,"remaining_time":0.04321427585},
{"learn":[3.13853824],"iteration":239,"passed_time":0.1699826377,"remaining_time":0.04249565943},
{"learn":[3.135212467],"iteration":240,"passed_time":0.1706676584,"remaining_time":0.04178170889},
{"learn":[3.133184242],"iteration":241,"passed_time":0.1713618159,"remaining_time":0.04107018729},
{"learn":[3.1310645],"iteration":242,"passed_time":0.1720675149,"remaining_time":0.04036151585},
{"learn":[3.129501801],"iteration":243,"passed_time":0.1727602895,"remaining_time":0.03964990252},
{"learn":[3.127383556],"iteration":244,"passed_time":0.1734548278,"remaining_time":0.0389388389},
{"learn":[3.125113552],"iteration":245,"passed_time":0.1741516704,"remaining_time":0.03822841545},
{"learn":[3.123451636],"iteration":246,"passed_time":0.1748336151,"remaining_time":0.03751490527},
{"learn":[3.121774329],"iteration":247,"passed_time":0.1755150389,"remaining_time":0.03680154041},
{"learn":[3.12064016],"iteration":248,"passed_time":0.1761930964,"remaining_time":0.03608774263},
{"learn":[3.118458735],"iteration":249,"passed_time":0.1768920126,"remaining_time":0.03537840252},
{"learn":[3.118087775],"iteration":250,"passed_time":0.1775115714,"remaining_time":0.03465365339},
{"learn":[3.116428243],"iteration":251,"passed_time":0.178226878,"remaining_time":0.03394797677},
{"learn":[3.114700101],"iteration":252,"passed_time":0.1788994155,"remaining_time":0.03323427877},
{"learn":[3.11347319],"iteration":253,"passed_time":0.1795626255,"remaining_time":0.03251921564},
{"learn":[3.113240315],"iteration":254,"passed_time":0.1802168588,"remaining_time":0.03180297509},
{"learn":[3.111387949],"iteration":255,"passed_time":0.1809018795,"remaining_time":0.03109251053},
{"learn":[3.11026213],"iteration":256,"passed_time":0.181583724,"remaining_time":0.03038171258},
{"learn":[3.108974007],"iteration":257,"passed_time":0.1822408725,"remaining_time":0.02966711879},
{"learn":[3.107380115],"iteration":258,"passed_time":0.1829314733,"remaining_time":0.02895826412},
{"learn":[3.105916539],"iteration":259,"passed_time":0.1836135285,"remaining_time":0.02824823515},
{"learn":[3.104417736],"iteration":260,"passed_time":0.1842718694,"remaining_time":0.02753487704},
{"learn":[3.102122718],"iteration":261,"passed_time":0.1849466809,"remaining_time":0.02682432777},
{"learn":[3.101112494],"iteration":262,"passed_time":0.1856380133,"remaining_time":0.02611637449},
{"learn":[3.099566808],"iteration":263,"passed_time":0.1863104702,"remaining_time":0.02540597321},
{"learn":[3.096889083],"iteration":264,"passed_time":0.1870164096,"remaining_time":0.02470028052},
{"learn":[3.094272078],"iteration":265,"passed_time":0.1877308747,"remaining_time":0.02399567571},
{"learn":[3.092678404],"iteration":266,"passed_time":0.1884692138,"remaining_time":0.02329394777},
{"learn":[3.091270094],"iteration":267,"passed_time":0.1891100823,"remaining_time":0.02258030834},
{"learn":[3.089342223],"iteration":268,"passed_time":0.1897945317,"remaining_time":0.02187223228},
{"learn":[3.088359046],"iteration":269,"passed_time":0.1904836399,"remaining_time":0.02116484888},
{"learn":[3.087064433],"iteration":270,"passed_time":0.1911422516,"remaining_time":0.02045433688},
{"learn":[3.08581245],"iteration":271,"passed_time":0.1917944211,"remaining_time":0.01974354335},
{"learn":[3.083964085],"iteration":272,"passed_time":0.192474302,"remaining_time":0.01903591998},
{"learn":[3.082283138],"iteration":273,"passed_time":0.1931399868,"remaining_time":0.01832715203},
{"learn":[3.081135419],"iteration":274,"passed_time":0.19379405,"remaining_time":0.01761764091},
{"learn":[3.081044423],"iteration":275,"passed_time":0.1944351991,"remaining_time":0.01690740861},
{"learn":[3.078172109],"iteration":276,"passed_time":0.1951310496,"remaining_time":0.01620221711},
{"learn":[3.076248239],"iteration":277,"passed_time":0.1958290539,"remaining_time":0.01549726326},
{"learn":[3.074057966],"iteration":278,"passed_time":0.1965432883,"remaining_time":0.01479358084},
{"learn":[3.071240797],"iteration":279,"passed_time":0.1972301221,"remaining_time":0.01408786586},
{"learn":[3.070011814],"iteration":280,"passed_time":0.1979112453,"remaining_time":0.01338189915},
{"learn":[3.067721247],"iteration":281,"passed_time":0.198583993,"remaining_time":0.01267557402},
{"learn":[3.066199855],"iteration":282,"passed_time":0.199262201,"remaining_time":0.01196981419},
{"learn":[3.064884916],"iteration":283,"passed_time":0.199927054,"remaining_time":0.011263496},
{"learn":[3.063454743],"iteration":284,"passed_time":0.2005851745,"remaining_time":0.01055711445},
{"learn":[3.062281421],"iteration":285,"passed_time":0.2012632922,"remaining_time":0.009852049267},
{"learn":[3.059709973],"iteration":286,"passed_time":0.2019772563,"remaining_time":0.009148795581},
{"learn":[3.058582573],"iteration":287,"passed_time":0.2026373806,"remaining_time":0.00844322419},
{"learn":[3.057098173],"iteration":288,"passed_time":0.2033028147,"remaining_time":0.007738169416},
{"learn":[3.055780095],"iteration":289,"passed_time":0.2039989657,"remaining_time":0.007034447094},
{"learn":[3.053656411],"iteration":290,"passed_time":0.2047093031,"remaining_time":0.00633121556},
{"learn":[3.052243959],"iteration":291,"passed_time":0.2053768612,"remaining_time":0.00562676332},
{"learn":[3.050769015],"iteration":292,"passed_time":0.2060605393,"remaining_time":0.004922948038},
{"learn":[3.047923059],"iteration":293,"passed_time":0.2067403801,"remaining_time":0.004219191431},
{"learn":[3.046397068],"iteration":294,"passed_time":0.2074533522,"remaining_time":0.003516158512},
{"learn":[3.045404689],"iteration":295,"passed_time":0.2081218119,"remaining_time":0.002812456918},
{"learn":[3.043526579],"iteration":296,"passed_time":0.2088015023,"remaining_time":0.002109106084},
{"learn":[3.041914198],"iteration":297,"passed_time":0.2094878552,"remaining_time":0.00140595876},
{"learn":[3.040607184],"iteration":298,"passed_time":0.2101355065,"remaining_time":0.0007027943362},
{"learn":[3.038991903],"iteration":299,"passed_time":0.2108371478,"remaining_time":0}
]}